LICENSE
README.md
setup.py
aiolo.egg-info/PKG-INFO
aiolo.egg-info/SOURCES.txt
aiolo.egg-info/dependency_links.txt
aiolo.egg-info/not-zip-safe
aiolo.egg-info/requires.txt
aiolo.egg-info/top_level.txt
src/aiolo/__init__.py
src/aiolo/__version__.py
src/aiolo/abstractservers.c
src/aiolo/abstractservers.pxd
src/aiolo/abstractservers.pyx
src/aiolo/abstractspecs.c
src/aiolo/abstractspecs.pxd
src/aiolo/abstractspecs.pyx
src/aiolo/addresses.c
src/aiolo/addresses.pxd
src/aiolo/addresses.pyx
src/aiolo/aioservers.c
src/aiolo/aioservers.pxd
src/aiolo/aioservers.pyx
src/aiolo/exceptions.py
src/aiolo/ips.py
src/aiolo/lo.c
src/aiolo/lo.pxd
src/aiolo/lo.pyx
src/aiolo/logs.py
src/aiolo/messages.c
src/aiolo/messages.pxd
src/aiolo/messages.pyx
src/aiolo/midis.c
src/aiolo/midis.pxd
src/aiolo/midis.pyx
src/aiolo/multicastaddresses.c
src/aiolo/multicastaddresses.pxd
src/aiolo/multicastaddresses.pyx
src/aiolo/multicasts.c
src/aiolo/multicasts.pxd
src/aiolo/multicasts.pyx
src/aiolo/pack.c
src/aiolo/pack.pxd
src/aiolo/pack.pyx
src/aiolo/paths.c
src/aiolo/paths.pxd
src/aiolo/paths.pyx
src/aiolo/patterns.py
src/aiolo/protos.py
src/aiolo/routes.pxd
src/aiolo/routes.py
src/aiolo/subs.py
src/aiolo/subsasynciterators.py
src/aiolo/threadedservers.c
src/aiolo/threadedservers.pxd
src/aiolo/threadedservers.pyx
src/aiolo/timetags.c
src/aiolo/timetags.pxd
src/aiolo/timetags.pyx
src/aiolo/types.py
src/aiolo/typespecs.c
src/aiolo/typespecs.pxd
src/aiolo/typespecs.pyx