Metadata-Version: 2.1
Name: aiolo
Version: 4.1.1
Summary: asyncio-friendly Python bindings for liblo
Home-page: https://github.com/elijahr/aiolo
Author: Elijah Shaw-Rutschman
Author-email: elijahr+aiolo@gmail.com
License: UNKNOWN
Platform: UNKNOWN
Classifier: Topic :: Multimedia :: Sound/Audio
Classifier: Framework :: AsyncIO
Classifier: Operating System :: MacOS :: MacOS X
Classifier: Operating System :: POSIX :: Linux
Classifier: Programming Language :: Python :: 3
Classifier: Programming Language :: Python :: Implementation :: PyPy
Classifier: Programming Language :: Python :: Implementation :: CPython
Classifier: License :: OSI Approved :: BSD License
Provides-Extra: examples
Provides-Extra: test
Provides-Extra: dev
